setup.cfg
setup.py
oxdpython/__init__.py
oxdpython/client.py
oxdpython/configurer.py
oxdpython/exceptions.py
oxdpython/messenger.py
oxdpython/utils.py
oxdpython.egg-info/PKG-INFO
oxdpython.egg-info/SOURCES.txt
oxdpython.egg-info/dependency_links.txt
oxdpython.egg-info/not-zip-safe
oxdpython.egg-info/top_level.txt